clickjacking/__init__.py
clickjacking/clickjacking.py
dns_lookup/__init__.py
dns_lookup/dns_lookup.py
exec_shell_command/__init__.py
exec_shell_command/exec_shell_command.py
http_headers_grabber/__init__.py
http_headers_grabber/http_headers_grabber.py
ip/__init__.py
ip/ip.py
ip_info_finder/__init__.py
ip_info_finder/ip_info_finder.py
logger/__init__.py
logger/formatter.py
logger/logger.py
nmap_scanner/__init__.py
nmap_scanner/nmap_scanner.py
one_sec_mail/__init__.py
one_sec_mail/one_sec_mail.py
phone_info/__init__.py
phone_info/phone_info.py
pwned/__init__.py
pwned/pwned.py
robots_scanner/__init__.py
robots_scanner/robots_scanner.py
whois_lookup/__init__.py
whois_lookup/whois_lookup.py
gods_eye-1.2.0.dist-info/LICENCE
gods_eye-1.2.0.dist-info/METADATA
gods_eye-1.2.0.dist-info/WHEEL
gods_eye-1.2.0.dist-info/top_level.txt
gods_eye-1.2.0.dist-info/RECORD
