Metadata-Version: 2.1
Name: gods_eye
Version: 1.2.0
Summary: A set of tools which should be used in Gods Eye
Home-page: https://github.com/paveldat/God-s-eye
Author: Pavel Dat
Author-email: dats.pavel1999@gmail.com
License-File: LICENCE
Requires-Dist: requests>=2.25.1
Requires-Dist: dnspython>=2.2.1
Requires-Dist: python-nmap>=0.7.1
Requires-Dist: folium>=0.14.0
Requires-Dist: opencage>=2.1.0
Requires-Dist: phonenumbers>=8.13.2
